allin/__init__.py
allin/app.py
allin/context.py
allin/errors.py
allin/globals.py
allin/handlers.py
allin/local.py
allin/params.py
allin/parser.py
allin/py.typed
allin/request.py
allin/response.py
allin/routing.py
allin/status.py
allin/stream.py
allin/validators.py
allin-0.1.1a1.dist-info/LICENSE
allin-0.1.1a1.dist-info/METADATA
allin-0.1.1a1.dist-info/WHEEL
allin-0.1.1a1.dist-info/RECORD
