Metadata-Version: 2.1
Name: allin
Version: 0.1.1a1
Summary: Allin is an experimental asynchronous web framework.
Home-page: https://github.com/aprilahijriyan/allin
License: MIT
Keywords: asgi,framework
Author: Aprila Hijriyan
Author-email: hijriyan23@gmail.com
Requires-Python: >=3.8,<4.0
Classifier: Development Status :: 4 - Beta
Classifier: Environment :: Web Environment
Classifier: Intended Audience :: Developers
Classifier: License :: OSI Approved :: MIT License
Classifier: Operating System :: OS Independent
Classifier: Programming Language :: Python
Classifier: Programming Language :: Python :: 3
Classifier: Programming Language :: Python :: 3.8
Classifier: Programming Language :: Python :: 3.9
Classifier: Programming Language :: Python :: 3.10
Classifier: Programming Language :: Python :: 3.11
Classifier: Topic :: Software Development :: Libraries :: Application Frameworks
Requires-Dist: aiofiles (>=22.1.0,<23.0.0)
Requires-Dist: autoroutes (>=0.3.5,<0.4.0)
Requires-Dist: biscuits (>=0.3.0,<0.4.0)
Requires-Dist: fast-query-parsers (>=0.3.0,<0.4.0)
Requires-Dist: jetblack-asgi-typing (>=0.4.0,<0.5.0)
Requires-Dist: msgspec (>=0.13.1,<0.14.0)
Requires-Dist: python-multipart (>=0.0.5,<0.0.6)
Requires-Dist: typing-extensions (>=4.2.0,<5.0.0)
Project-URL: Repository, https://github.com/aprilahijriyan/allin
